
{"items":[{"name":"GRILO.Boot","href":"GRILO.Boot.html","topicHref":"GRILO.Boot.html","topicUid":"GRILO.Boot","items":[{"name":"IBootable","href":"GRILO.Boot.IBootable.html","topicHref":"GRILO.Boot.IBootable.html","topicUid":"GRILO.Boot.IBootable"}]},{"name":"GRILO.BootableAppDemo","href":"GRILO.BootableAppDemo.html","topicHref":"GRILO.BootableAppDemo.html","topicUid":"GRILO.BootableAppDemo","items":[{"name":"BootClass","href":"GRILO.BootableAppDemo.BootClass.html","topicHref":"GRILO.BootableAppDemo.BootClass.html","topicUid":"GRILO.BootableAppDemo.BootClass"}]},{"name":"GRILO.Bootloader.Boot.Apps","href":"GRILO.Bootloader.Boot.Apps.html","topicHref":"GRILO.Bootloader.Boot.Apps.html","topicUid":"GRILO.Bootloader.Boot.Apps","items":[{"name":"BootAppInfo","href":"GRILO.Bootloader.Boot.Apps.BootAppInfo.html","topicHref":"GRILO.Bootloader.Boot.Apps.BootAppInfo.html","topicUid":"GRILO.Bootloader.Boot.Apps.BootAppInfo"},{"name":"BootManager","href":"GRILO.Bootloader.Boot.Apps.BootManager.html","topicHref":"GRILO.Bootloader.Boot.Apps.BootManager.html","topicUid":"GRILO.Bootloader.Boot.Apps.BootManager"}]},{"name":"GRILO.Bootloader.Boot.Diagnostics","href":"GRILO.Bootloader.Boot.Diagnostics.html","topicHref":"GRILO.Bootloader.Boot.Diagnostics.html","topicUid":"GRILO.Bootloader.Boot.Diagnostics","items":[{"name":"DiagnosticsLevel","href":"GRILO.Bootloader.Boot.Diagnostics.DiagnosticsLevel.html","topicHref":"GRILO.Bootloader.Boot.Diagnostics.DiagnosticsLevel.html","topicUid":"GRILO.Bootloader.Boot.Diagnostics.DiagnosticsLevel"},{"name":"DiagnosticsWriter","href":"GRILO.Bootloader.Boot.Diagnostics.DiagnosticsWriter.html","topicHref":"GRILO.Bootloader.Boot.Diagnostics.DiagnosticsWriter.html","topicUid":"GRILO.Bootloader.Boot.Diagnostics.DiagnosticsWriter"}]},{"name":"GRILO.Bootloader.Boot.Style","href":"GRILO.Bootloader.Boot.Style.html","topicHref":"GRILO.Bootloader.Boot.Style.html","topicUid":"GRILO.Bootloader.Boot.Style","items":[{"name":"BaseBootStyle","href":"GRILO.Bootloader.Boot.Style.BaseBootStyle.html","topicHref":"GRILO.Bootloader.Boot.Style.BaseBootStyle.html","topicUid":"GRILO.Bootloader.Boot.Style.BaseBootStyle"},{"name":"BootStyleManager","href":"GRILO.Bootloader.Boot.Style.BootStyleManager.html","topicHref":"GRILO.Bootloader.Boot.Style.BootStyleManager.html","topicUid":"GRILO.Bootloader.Boot.Style.BootStyleManager"},{"name":"IBootStyle","href":"GRILO.Bootloader.Boot.Style.IBootStyle.html","topicHref":"GRILO.Bootloader.Boot.Style.IBootStyle.html","topicUid":"GRILO.Bootloader.Boot.Style.IBootStyle"}]},{"name":"GRILO.Bootloader.Common","href":"GRILO.Bootloader.Common.html","topicHref":"GRILO.Bootloader.Common.html","topicUid":"GRILO.Bootloader.Common","items":[{"name":"BootloaderException","href":"GRILO.Bootloader.Common.BootloaderException.html","topicHref":"GRILO.Bootloader.Common.BootloaderException.html","topicUid":"GRILO.Bootloader.Common.BootloaderException"},{"name":"BootloaderState","href":"GRILO.Bootloader.Common.BootloaderState.html","topicHref":"GRILO.Bootloader.Common.BootloaderState.html","topicUid":"GRILO.Bootloader.Common.BootloaderState"}]},{"name":"GRILO.Bootloader.Common.Configuration","href":"GRILO.Bootloader.Common.Configuration.html","topicHref":"GRILO.Bootloader.Common.Configuration.html","topicUid":"GRILO.Bootloader.Common.Configuration","items":[{"name":"Config","href":"GRILO.Bootloader.Common.Configuration.Config.html","topicHref":"GRILO.Bootloader.Common.Configuration.Config.html","topicUid":"GRILO.Bootloader.Common.Configuration.Config"},{"name":"ConfigPaths","href":"GRILO.Bootloader.Common.Configuration.ConfigPaths.html","topicHref":"GRILO.Bootloader.Common.Configuration.ConfigPaths.html","topicUid":"GRILO.Bootloader.Common.Configuration.ConfigPaths"}]},{"name":"GRILO.Bootloader.Common.Configuration.Instance","href":"GRILO.Bootloader.Common.Configuration.Instance.html","topicHref":"GRILO.Bootloader.Common.Configuration.Instance.html","topicUid":"GRILO.Bootloader.Common.Configuration.Instance","items":[{"name":"ConfigInstance","href":"GRILO.Bootloader.Common.Configuration.Instance.ConfigInstance.html","topicHref":"GRILO.Bootloader.Common.Configuration.Instance.ConfigInstance.html","topicUid":"GRILO.Bootloader.Common.Configuration.Instance.ConfigInstance"}]}],"memberLayout":"SamePage"}
